LICENSE.txt
MANIFEST.in
README.rst
readme.rst
requirements.txt
setup.py
angora/__init__.py
angora/zzz_manual_install.py
angora.egg-info/PKG-INFO
angora.egg-info/SOURCES.txt
angora.egg-info/dependency_links.txt
angora.egg-info/top_level.txt
angora/__pycache__/__init__.cpython-33.pyc
angora/algorithm/__init__.py
angora/algorithm/binarysearch.py
angora/algorithm/iterable.py
angora/baseclass/__init__.py
angora/baseclass/classtree.py
angora/baseclass/defaultExc.py
angora/baseclass/nameddict.py
angora/bot/__init__.py
angora/bot/anjian.py
angora/bot/macro.py
angora/crawler/__init__.py
angora/crawler/downloader.py
angora/crawler/simplecrawler.py
angora/dataIO/__init__.py
angora/dataIO/js.py
angora/dataIO/pk.py
angora/dataIO/textfile.py
angora/dataIO/testdata/multilanguage.txt
angora/dtypes/__init__.py
angora/dtypes/dicttree.py
angora/dtypes/orderedset.py
angora/filesystem/__init__.py
angora/filesystem/filesystem.py
angora/filesystem/test.txt
angora/filesystem/winzip.py
angora/filesystem/testdir/root_file.txt
angora/filesystem/testdir/root_image.jpg
angora/filesystem/testdir/subfolder/sub_file.txt
angora/filesystem/testdir/subfolder/sub_image.jpg
angora/gadget/__init__.py
angora/gadget/backup.py
angora/gadget/codestats.py
angora/gadget/configuration.py
angora/gadget/controlflow.py
angora/gadget/logger.py
angora/gadget/messenger.py
angora/gadget/pytimer.py
angora/gadget/testdata/config.txt
angora/hashes/__init__.py
angora/hashes/fingerprint.py
angora/markup/__init__.py
angora/markup/html.py
angora/markup/rst.py
angora/markup/rst_syntax_example/Block quotes.rst
angora/markup/rst_syntax_example/Footnotes.rst
angora/markup/rst_syntax_example/Line blocks.rst
angora/markup/rst_syntax_example/Link to a header.rst
angora/markup/rst_syntax_example/Link to anywhere you want.rst
angora/markup/rst_syntax_example/Table.rst
angora/math/__init__.py
angora/math/img2waveform.py
angora/math/interp.py
angora/math/outlier.py
angora/math/testdata/img2waveform/asciiart.txt
angora/math/testdata/img2waveform/rabbit.png
angora/math/testdata/img2waveform/waveform.png
angora/py23/__init__.py
angora/text/__init__.py
