Metadata-Version: 1.1
Name: angora
Version: 0.0.2
Summary: Sanhe's Data Science/Python Dev toolkits
Home-page: https://github.com/MacHu-GWU/angora-project
Author: Sanhe Hu
Author-email: husanhe@gmail.com
License: MIT
Download-URL: https://github.com/MacHu-GWU/angora-project/tarball/2016-02-16
Platform: Windows
Platform: MacOS
Platform: Unix
Classifier: Development Status :: 4 - Beta
Classifier: Intended Audience :: Developers
Classifier: License :: OSI Approved :: MIT License
Classifier: Natural Language :: English
Classifier: Operating System :: Microsoft :: Windows
Classifier: Operating System :: MacOS
Classifier: Operating System :: Unix
Classifier: Programming Language :: Python
Classifier: Programming Language :: Python :: 2
Classifier: Programming Language :: Python :: 2.7
Classifier: Programming Language :: Python :: 3
Classifier: Programming Language :: Python :: 3.3
Classifier: Programming Language :: Python :: 3.4
